app/__init__.py
app/config.py
app/installer.py
app/logging_config.py
app/server.py
app/manager/__init__.py
app/manager/state_cache.py
app/models/__init__.py
app/models/outbox_event.py
app/models/project.py
app/repositories/__init__.py
app/repositories/outbox_repository.py
app/repositories/project_repository.py
app/services/__init__.py
app/services/db_service.py
app/services/notification_service.py
app/services/outbox_worker.py
app/services/path_validator.py
app/services/watchdog_service.py
app/tools/__init__.py
app/tools/base.py
app/tools/project_tools.py
app/tools/sync_tools.py
jtech_bridge_mcp-1.0.0.dist-info/METADATA
jtech_bridge_mcp-1.0.0.dist-info/WHEEL
jtech_bridge_mcp-1.0.0.dist-info/entry_points.txt
jtech_bridge_mcp-1.0.0.dist-info/RECORD
