Metadata-Version: 2.4
Name: jtech-bridge-mcp
Version: 1.0.0
Summary: Jtech MCP Server for IDE synchronization - Bridge between Backend and Frontend development
Author-email: Jtech <dev@jtech.com>
License: MIT
Keywords: anthropic,bridge,ide,jtech,mcp,sync
Classifier: Development Status :: 4 - Beta
Classifier: Intended Audience :: Developers
Classifier: License :: OSI Approved :: MIT License
Classifier: Programming Language :: Python :: 3.12
Classifier: Topic :: Software Development :: Libraries :: Python Modules
Requires-Python: >=3.12
Requires-Dist: distro>=1.9.0
Requires-Dist: fasteners>=0.19
Requires-Dist: mcp>=1.0.0
Requires-Dist: motor>=3.3.0
Requires-Dist: pydantic-settings>=2.0.0
Requires-Dist: pydantic>=2.0.0
Requires-Dist: python-dotenv>=1.0.0
Requires-Dist: watchdog>=4.0.0
Provides-Extra: dev
Requires-Dist: build>=1.0.0; extra == 'dev'
Requires-Dist: mypy>=1.8.0; extra == 'dev'
Requires-Dist: pre-commit>=3.7.0; extra == 'dev'
Requires-Dist: pytest-asyncio>=0.23.0; extra == 'dev'
Requires-Dist: pytest-cov>=4.0.0; extra == 'dev'
Requires-Dist: pytest-mock>=3.12.0; extra == 'dev'
Requires-Dist: pytest>=8.0.0; extra == 'dev'
Requires-Dist: ruff>=0.4.0; extra == 'dev'
Requires-Dist: twine>=5.0.0; extra == 'dev'
